README
narratoapi.py
setup.py
py_narrato.egg-info/PKG-INFO
py_narrato.egg-info/SOURCES.txt
py_narrato.egg-info/dependency_links.txt
py_narrato.egg-info/top_level.txt