Metadata-Version: 1.0
Name: py-narrato
Version: 0.1
Summary: Minimal Narrato API client for Python.
Home-page: http://github.com/narrato/py-narrato/
Author: Narrato Team
Author-email: team@narrato.co
License: Apache 2
Platform: UNKNOWN
